llama_index/packs/multi_document_agents/__init__.py
llama_index/packs/multi_document_agents/base.py
llama_index_packs_multi_document_agents-0.4.1.dist-info/METADATA
llama_index_packs_multi_document_agents-0.4.1.dist-info/WHEEL
llama_index_packs_multi_document_agents-0.4.1.dist-info/licenses/LICENSE
llama_index_packs_multi_document_agents-0.4.1.dist-info/RECORD
