Metadata-Version: 2.4
Name: llama-index-packs-multi-document-agents
Version: 0.4.1
Summary: llama-index packs multi_document_agents integration
Author-email: Your Name <you@example.com>
Maintainer: jerryjliu
License-Expression: MIT
License-File: LICENSE
Keywords: agents,document,multi
Requires-Python: <4.0,>=3.9
Requires-Dist: llama-index-agent-openai-legacy<0.4,>=0.3.0
Requires-Dist: llama-index-agent-openai<0.5,>=0.4.0
Requires-Dist: llama-index-core<0.13,>=0.12.0
Requires-Dist: llama-index-llms-openai<0.5,>=0.4.0
